{
  "city": "广州",
  "queryTime": "2026-05-04T16:18:03.038Z",
  "line": {
    "name": "地铁5号线(滘口--黄埔新港)",
    "id": "440100023037",
    "startStation": "滘口",
    "endStation": "黄埔新港",
    "distance": "41.382000",
    "stationCount": 30,
    "path": [
      [
        113.20844,
        23.113796
      ],
      [
        113.209015,
        23.11462
      ],
      [
        113.209467,
        23.115237
      ],
      [
        113.210103,
        23.116137
      ],
      [
        113.210261,
        23.116298
      ],
      [
        113.210432,
        23.116476
      ],
      [
        113.210658,
        23.116653
      ],
      [
        113.2118,
        23.117352
      ],
      [
        113.212052,
        23.117522
      ],
      [
        113.21224,
        23.11768
      ],
      [
        113.212471,
        23.117955
      ],
      [
        113.214016,
        23.120268
      ],
      [
        113.214675,
        23.121265
      ],
      [
        113.215625,
        23.122939
      ],
      [
        113.215818,
        23.123269
      ],
      [
        113.216006,
        23.123551
      ],
      [
        113.216312,
        23.123886
      ],
      [
        113.216553,
        23.124118
      ],
      [
        113.216854,
        23.12436
      ],
      [
        113.217154,
        23.124567
      ],
      [
        113.217503,
        23.124759
      ],
      [
        113.218387,
        23.125234
      ],
      [
        113.21914,
        23.125642
      ],
      [
        113.21935,
        23.12576
      ],
      [
        113.219575,
        23.125869
      ],
      [
        113.219849,
        23.125987
      ],
      [
        113.22009,
        23.126081
      ],
      [
        113.220423,
        23.126174
      ],
      [
        113.220742,
        23.126241
      ],
      [
        113.221064,
        23.126285
      ],
      [
        113.222142,
        23.126389
      ],
      [
        113.222926,
        23.126417
      ],
      [
        113.223516,
        23.126392
      ],
      [
        113.225358,
        23.126337
      ],
      [
        113.225889,
        23.126308
      ],
      [
        113.226377,
        23.126258
      ],
      [
        113.226833,
        23.126155
      ],
      [
        113.227418,
        23.125918
      ],
      [
        113.227991,
        23.125592
      ],
      [
        113.228276,
        23.12547
      ],
      [
        113.228579,
        23.125338
      ],
      [
        113.228865,
        23.125225
      ],
      [
        113.229164,
        23.125128
      ],
      [
        113.229531,
        23.125013
      ],
      [
        113.230004,
        23.124943
      ],
      [
        113.230535,
        23.124972
      ],
      [
        113.231021,
        23.125032
      ],
      [
        113.23163,
        23.125185
      ],
      [
        113.23215,
        23.125339
      ],
      [
        113.23252,
        23.125545
      ],
      [
        113.233357,
        23.126307
      ],
      [
        113.233891,
        23.126802
      ],
      [
        113.23406,
        23.126977
      ],
      [
        113.234139,
        23.127073
      ],
      [
        113.234246,
        23.127206
      ],
      [
        113.234371,
        23.127373
      ],
      [
        113.235056,
        23.128358
      ],
      [
        113.236658,
        23.131779
      ],
      [
        113.236973,
        23.13281
      ],
      [
        113.237242,
        23.133691
      ],
      [
        113.237511,
        23.134985
      ],
      [
        113.237783,
        23.136656
      ],
      [
        113.238056,
        23.137381
      ],
      [
        113.238328,
        23.138106
      ],
      [
        113.238909,
        23.139613
      ],
      [
        113.239108,
        23.140038
      ],
      [
        113.239317,
        23.140363
      ],
      [
        113.239467,
        23.140565
      ],
      [
        113.239596,
        23.140683
      ],
      [
        113.239758,
        23.140789
      ],
      [
        113.23991,
        23.140876
      ],
      [
        113.241197,
        23.141653
      ],
      [
        113.241576,
        23.141888
      ],
      [
        113.242125,
        23.142222
      ],
      [
        113.242531,
        23.142481
      ],
      [
        113.242811,
        23.142661
      ],
      [
        113.246847,
        23.145166
      ],
      [
        113.248905,
        23.146357
      ],
      [
        113.249463,
        23.146615
      ],
      [
        113.249996,
        23.146835
      ],
      [
        113.250731,
        23.147113
      ],
      [
        113.251357,
        23.147321
      ],
      [
        113.251696,
        23.147421
      ],
      [
        113.252041,
        23.147495
      ],
      [
        113.252386,
        23.14759
      ],
      [
        113.252769,
        23.147671
      ],
      [
        113.253057,
        23.147722
      ],
      [
        113.253327,
        23.147765
      ],
      [
        113.253589,
        23.147804
      ],
      [
        113.25391,
        23.147882
      ],
      [
        113.254215,
        23.147954
      ],
      [
        113.254623,
        23.148033
      ],
      [
        113.254881,
        23.14806
      ],
      [
        113.25543,
        23.148112
      ],
      [
        113.25575,
        23.148151
      ],
      [
        113.25594,
        23.148176
      ],
      [
        113.256141,
        23.148183
      ],
      [
        113.25634,
        23.148173
      ],
      [
        113.25667,
        23.148089
      ],
      [
        113.25717,
        23.147864
      ],
      [
        113.257705,
        23.147627
      ],
      [
        113.258046,
        23.147465
      ],
      [
        113.258335,
        23.147344
      ],
      [
        113.258663,
        23.147196
      ],
      [
        113.25899,
        23.147085
      ],
      [
        113.259414,
        23.146962
      ],
      [
        113.260025,
        23.146784
      ],
      [
        113.260625,
        23.146616
      ],
      [
        113.263461,
        23.14576
      ],
      [
        113.264566,
        23.145464
      ],
      [
        113.265164,
        23.145309
      ],
      [
        113.265497,
        23.145183
      ],
      [
        113.265789,
        23.145016
      ],
      [
        113.266084,
        23.144818
      ],
      [
        113.266377,
        23.144596
      ],
      [
        113.26678,
        23.144226
      ],
      [
        113.267258,
        23.143798
      ],
      [
        113.267847,
        23.14332
      ],
      [
        113.268563,
        23.142755
      ],
      [
        113.269463,
        23.142134
      ],
      [
        113.269787,
        23.141941
      ],
      [
        113.270105,
        23.14176
      ],
      [
        113.27119,
        23.141184
      ],
      [
        113.272406,
        23.140565
      ],
      [
        113.273196,
        23.140158
      ],
      [
        113.27357,
        23.139969
      ],
      [
        113.273754,
        23.139888
      ],
      [
        113.273927,
        23.139822
      ],
      [
        113.274076,
        23.139768
      ],
      [
        113.274241,
        23.139713
      ],
      [
        113.274445,
        23.139659
      ],
      [
        113.274598,
        23.139621
      ],
      [
        113.274761,
        23.139587
      ],
      [
        113.274897,
        23.139566
      ],
      [
        113.275103,
        23.13954
      ],
      [
        113.275398,
        23.139518
      ],
      [
        113.276905,
        23.139424
      ],
      [
        113.278419,
        23.139327
      ],
      [
        113.279094,
        23.139221
      ],
      [
        113.280034,
        23.13883
      ],
      [
        113.285809,
        23.136636
      ],
      [
        113.286561,
        23.136378
      ],
      [
        113.287298,
        23.136124
      ],
      [
        113.288316,
        23.135806
      ],
      [
        113.288767,
        23.135687
      ],
      [
        113.289335,
        23.135564
      ],
      [
        113.290081,
        23.135421
      ],
      [
        113.290939,
        23.135273
      ],
      [
        113.291722,
        23.135145
      ],
      [
        113.293069,
        23.134898
      ],
      [
        113.295086,
        23.134553
      ],
      [
        113.295354,
        23.134523
      ],
      [
        113.295569,
        23.134498
      ],
      [
        113.29579,
        23.134483
      ],
      [
        113.296681,
        23.134486
      ],
      [
        113.297627,
        23.134484
      ],
      [
        113.302582,
        23.13453
      ],
      [
        113.305668,
        23.134653
      ],
      [
        113.306439,
        23.134692
      ],
      [
        113.306922,
        23.13472
      ],
      [
        113.307292,
        23.134713
      ],
      [
        113.307697,
        23.134714
      ],
      [
        113.307995,
        23.134694
      ],
      [
        113.308368,
        23.13465
      ],
      [
        113.308703,
        23.134561
      ],
      [
        113.308931,
        23.13448
      ],
      [
        113.309087,
        23.134387
      ],
      [
        113.309191,
        23.134276
      ],
      [
        113.309313,
        23.134153
      ],
      [
        113.309433,
        23.134022
      ],
      [
        113.309557,
        23.133847
      ],
      [
        113.309659,
        23.133679
      ],
      [
        113.309723,
        23.133551
      ],
      [
        113.309776,
        23.133359
      ],
      [
        113.309792,
        23.133147
      ],
      [
        113.309765,
        23.132901
      ],
      [
        113.309679,
        23.132417
      ],
      [
        113.309183,
        23.131399
      ],
      [
        113.308544,
        23.13062
      ],
      [
        113.308169,
        23.130186
      ],
      [
        113.307907,
        23.1298
      ],
      [
        113.307717,
        23.129381
      ],
      [
        113.307623,
        23.129066
      ],
      [
        113.307536,
        23.12874
      ],
      [
        113.307481,
        23.128415
      ],
      [
        113.30743,
        23.128054
      ],
      [
        113.307451,
        23.127835
      ],
      [
        113.307497,
        23.12765
      ],
      [
        113.307544,
        23.127493
      ],
      [
        113.30779,
        23.127004
      ],
      [
        113.308011,
        23.126551
      ],
      [
        113.309037,
        23.124614
      ],
      [
        113.309984,
        23.123045
      ],
      [
        113.31117,
        23.120914
      ],
      [
        113.311379,
        23.120598
      ],
      [
        113.31154,
        23.120396
      ],
      [
        113.311717,
        23.120233
      ],
      [
        113.311915,
        23.120104
      ],
      [
        113.312135,
        23.120016
      ],
      [
        113.312382,
        23.119942
      ],
      [
        113.312672,
        23.119887
      ],
      [
        113.313058,
        23.119853
      ],
      [
        113.313656,
        23.119834
      ],
      [
        113.314249,
        23.119843
      ],
      [
        113.314847,
        23.119853
      ],
      [
        113.31677,
        23.119715
      ],
      [
        113.319564,
        23.119425
      ],
      [
        113.320002,
        23.119386
      ],
      [
        113.320586,
        23.119365
      ],
      [
        113.321202,
        23.119366
      ],
      [
        113.321891,
        23.119367
      ],
      [
        113.322322,
        23.119365
      ],
      [
        113.322744,
        23.119343
      ],
      [
        113.323256,
        23.1193
      ],
      [
        113.324443,
        23.119152
      ],
      [
        113.326668,
        23.118952
      ],
      [
        113.329169,
        23.11875
      ],
      [
        113.331498,
        23.118582
      ],
      [
        113.332105,
        23.118539
      ],
      [
        113.332697,
        23.118502
      ],
      [
        113.338429,
        23.118002
      ],
      [
        113.341315,
        23.11768
      ],
      [
        113.344663,
        23.117464
      ],
      [
        113.345949,
        23.117366
      ],
      [
        113.347295,
        23.117264
      ],
      [
        113.35377,
        23.116557
      ],
      [
        113.362262,
        23.115288
      ],
      [
        113.362474,
        23.115275
      ],
      [
        113.362667,
        23.11527
      ],
      [
        113.362866,
        23.1153
      ],
      [
        113.363756,
        23.115515
      ],
      [
        113.364512,
        23.115699
      ],
      [
        113.367828,
        23.116526
      ],
      [
        113.369601,
        23.117306
      ],
      [
        113.370989,
        23.118106
      ],
      [
        113.371983,
        23.118772
      ],
      [
        113.373007,
        23.119194
      ],
      [
        113.374459,
        23.119488
      ],
      [
        113.375599,
        23.119542
      ],
      [
        113.376428,
        23.119458
      ],
      [
        113.377215,
        23.11928
      ],
      [
        113.377997,
        23.119099
      ],
      [
        113.383598,
        23.117878
      ],
      [
        113.38828,
        23.116402
      ],
      [
        113.389405,
        23.116067
      ],
      [
        113.390007,
        23.115856
      ],
      [
        113.391603,
        23.115286
      ],
      [
        113.393175,
        23.114624
      ],
      [
        113.394939,
        23.113812
      ],
      [
        113.395556,
        23.11339
      ],
      [
        113.395862,
        23.113117
      ],
      [
        113.396315,
        23.112695
      ],
      [
        113.397534,
        23.111355
      ],
      [
        113.398036,
        23.110882
      ],
      [
        113.398598,
        23.110557
      ],
      [
        113.400963,
        23.109623
      ],
      [
        113.401562,
        23.109392
      ],
      [
        113.402168,
        23.109158
      ],
      [
        113.407563,
        23.107128
      ],
      [
        113.410382,
        23.106071
      ],
      [
        113.411726,
        23.105571
      ],
      [
        113.413153,
        23.105026
      ],
      [
        113.415066,
        23.104365
      ],
      [
        113.415784,
        23.104098
      ],
      [
        113.41649,
        23.103833
      ],
      [
        113.422826,
        23.101261
      ],
      [
        113.425029,
        23.100523
      ],
      [
        113.425676,
        23.100435
      ],
      [
        113.426673,
        23.100365
      ],
      [
        113.429404,
        23.10038
      ],
      [
        113.431454,
        23.100347
      ],
      [
        113.432281,
        23.100343
      ],
      [
        113.433148,
        23.100339
      ],
      [
        113.436846,
        23.100395
      ],
      [
        113.439131,
        23.100424
      ],
      [
        113.440515,
        23.100444
      ],
      [
        113.441197,
        23.100493
      ],
      [
        113.441486,
        23.100544
      ],
      [
        113.441755,
        23.100613
      ],
      [
        113.441991,
        23.100697
      ],
      [
        113.442312,
        23.100865
      ],
      [
        113.443208,
        23.101383
      ],
      [
        113.444124,
        23.101943
      ],
      [
        113.445313,
        23.102712
      ],
      [
        113.446074,
        23.103227
      ],
      [
        113.446795,
        23.103714
      ],
      [
        113.447558,
        23.104202
      ],
      [
        113.448081,
        23.10453
      ],
      [
        113.448583,
        23.104831
      ],
      [
        113.449224,
        23.105171
      ],
      [
        113.44983,
        23.105455
      ],
      [
        113.451239,
        23.106056
      ],
      [
        113.451895,
        23.106257
      ],
      [
        113.452487,
        23.10638
      ],
      [
        113.453083,
        23.106478
      ],
      [
        113.453925,
        23.106562
      ],
      [
        113.454756,
        23.106587
      ],
      [
        113.455658,
        23.106538
      ],
      [
        113.456741,
        23.106424
      ],
      [
        113.457417,
        23.106339
      ],
      [
        113.458515,
        23.106216
      ],
      [
        113.459613,
        23.106104
      ],
      [
        113.46202,
        23.105959
      ],
      [
        113.463474,
        23.105776
      ],
      [
        113.464777,
        23.105409
      ],
      [
        113.468384,
        23.104037
      ],
      [
        113.469004,
        23.103796
      ],
      [
        113.46984,
        23.103473
      ],
      [
        113.470099,
        23.103387
      ],
      [
        113.470331,
        23.103329
      ],
      [
        113.473244,
        23.102174
      ],
      [
        113.47398,
        23.10187
      ],
      [
        113.474802,
        23.101605
      ],
      [
        113.475151,
        23.101447
      ],
      [
        113.475531,
        23.101129
      ],
      [
        113.475797,
        23.100702
      ],
      [
        113.475981,
        23.100267
      ],
      [
        113.476386,
        23.099711
      ],
      [
        113.47674,
        23.099162
      ],
      [
        113.477213,
        23.098766
      ],
      [
        113.477561,
        23.098453
      ],
      [
        113.477697,
        23.098379
      ],
      [
        113.477836,
        23.098325
      ],
      [
        113.478258,
        23.098275
      ],
      [
        113.47867,
        23.098269
      ],
      [
        113.479593,
        23.098267
      ],
      [
        113.480384,
        23.098281
      ],
      [
        113.480957,
        23.098282
      ],
      [
        113.481634,
        23.098246
      ],
      [
        113.482186,
        23.098182
      ],
      [
        113.482633,
        23.098124
      ],
      [
        113.483201,
        23.09803
      ],
      [
        113.484289,
        23.097877
      ],
      [
        113.485372,
        23.097722
      ],
      [
        113.486325,
        23.097559
      ],
      [
        113.487462,
        23.097347
      ],
      [
        113.488251,
        23.097198
      ],
      [
        113.48867,
        23.097067
      ],
      [
        113.489,
        23.096865
      ],
      [
        113.489205,
        23.096683
      ],
      [
        113.489345,
        23.096501
      ],
      [
        113.489511,
        23.096195
      ],
      [
        113.489989,
        23.095074
      ],
      [
        113.491061,
        23.092278
      ],
      [
        113.492257,
        23.090915
      ],
      [
        113.492978,
        23.090342
      ],
      [
        113.494431,
        23.089535
      ],
      [
        113.498737,
        23.088175
      ],
      [
        113.499796,
        23.087785
      ],
      [
        113.501398,
        23.086159
      ],
      [
        113.501748,
        23.085793
      ],
      [
        113.502726,
        23.084731
      ],
      [
        113.503744,
        23.08363
      ],
      [
        113.503865,
        23.083511
      ],
      [
        113.503941,
        23.083443
      ],
      [
        113.504017,
        23.083388
      ],
      [
        113.504121,
        23.083323
      ],
      [
        113.504225,
        23.083272
      ],
      [
        113.50436,
        23.083213
      ],
      [
        113.504495,
        23.083168
      ],
      [
        113.504852,
        23.083084
      ],
      [
        113.505182,
        23.083027
      ],
      [
        113.505599,
        23.082974
      ],
      [
        113.50608,
        23.082913
      ],
      [
        113.506995,
        23.082827
      ],
      [
        113.509748,
        23.082533
      ],
      [
        113.512096,
        23.082263
      ],
      [
        113.51266,
        23.082211
      ],
      [
        113.513102,
        23.08217
      ],
      [
        113.513557,
        23.08215
      ],
      [
        113.513999,
        23.082134
      ],
      [
        113.514453,
        23.082164
      ],
      [
        113.514855,
        23.082199
      ],
      [
        113.515292,
        23.082261
      ],
      [
        113.515853,
        23.082356
      ],
      [
        113.516445,
        23.082478
      ],
      [
        113.517408,
        23.082691
      ],
      [
        113.518376,
        23.082901
      ],
      [
        113.519374,
        23.083125
      ],
      [
        113.519675,
        23.083181
      ],
      [
        113.519875,
        23.083207
      ],
      [
        113.520125,
        23.083228
      ],
      [
        113.520378,
        23.083238
      ],
      [
        113.520702,
        23.083233
      ],
      [
        113.521001,
        23.083215
      ],
      [
        113.521161,
        23.083199
      ],
      [
        113.521327,
        23.083173
      ],
      [
        113.521511,
        23.083115
      ],
      [
        113.521626,
        23.083059
      ],
      [
        113.521724,
        23.08299
      ],
      [
        113.521828,
        23.082893
      ],
      [
        113.52192,
        23.082785
      ],
      [
        113.522734,
        23.0815
      ],
      [
        113.523665,
        23.079978
      ],
      [
        113.525366,
        23.077218
      ],
      [
        113.525435,
        23.077099
      ],
      [
        113.525487,
        23.076998
      ],
      [
        113.525703,
        23.076543
      ],
      [
        113.525788,
        23.076346
      ],
      [
        113.525847,
        23.076208
      ],
      [
        113.525881,
        23.076117
      ],
      [
        113.525904,
        23.076048
      ],
      [
        113.525918,
        23.076003
      ],
      [
        113.525932,
        23.075954
      ],
      [
        113.525947,
        23.075892
      ],
      [
        113.525955,
        23.075836
      ],
      [
        113.525968,
        23.075735
      ],
      [
        113.525974,
        23.075648
      ],
      [
        113.526056,
        23.074279
      ],
      [
        113.526131,
        23.072962
      ],
      [
        113.52613,
        23.072865
      ],
      [
        113.526124,
        23.072741
      ],
      [
        113.526112,
        23.072601
      ],
      [
        113.52541,
        23.065356
      ],
      [
        113.525377,
        23.064951
      ],
      [
        113.525322,
        23.064167
      ],
      [
        113.525278,
        23.063541
      ],
      [
        113.525232,
        23.062909
      ],
      [
        113.525203,
        23.062442
      ],
      [
        113.524909,
        23.053626
      ],
      [
        113.524896,
        23.053404
      ],
      [
        113.524819,
        23.052347
      ]
    ],
    "stations": [
      {
        "name": "滘口",
        "location": [
          113.20844,
          23.113796
        ],
        "sequence": 1
      },
      {
        "name": "坦尾",
        "location": [
          113.218387,
          23.125234
        ],
        "sequence": 2
      },
      {
        "name": "中山八",
        "location": [
          113.233357,
          23.126307
        ],
        "sequence": 3
      },
      {
        "name": "西场",
        "location": [
          113.238056,
          23.137381
        ],
        "sequence": 4
      },
      {
        "name": "西村",
        "location": [
          113.242125,
          23.142222
        ],
        "sequence": 5
      },
      {
        "name": "广州火车站",
        "location": [
          113.25717,
          23.147864
        ],
        "sequence": 6
      },
      {
        "name": "小北",
        "location": [
          113.276905,
          23.139424
        ],
        "sequence": 7
      },
      {
        "name": "淘金",
        "location": [
          113.286561,
          23.136378
        ],
        "sequence": 8
      },
      {
        "name": "区庄",
        "location": [
          113.296681,
          23.134486
        ],
        "sequence": 9
      },
      {
        "name": "动物园",
        "location": [
          113.307292,
          23.134713
        ],
        "sequence": 10
      },
      {
        "name": "杨箕",
        "location": [
          113.30779,
          23.127004
        ],
        "sequence": 11
      },
      {
        "name": "五羊邨",
        "location": [
          113.314249,
          23.119843
        ],
        "sequence": 12
      },
      {
        "name": "珠江新城",
        "location": [
          113.321202,
          23.119366
        ],
        "sequence": 13
      },
      {
        "name": "猎德",
        "location": [
          113.332105,
          23.118539
        ],
        "sequence": 14
      },
      {
        "name": "潭村",
        "location": [
          113.345949,
          23.117366
        ],
        "sequence": 15
      },
      {
        "name": "员村",
        "location": [
          113.363756,
          23.115515
        ],
        "sequence": 16
      },
      {
        "name": "科韵路",
        "location": [
          113.377215,
          23.11928
        ],
        "sequence": 17
      },
      {
        "name": "车陂南",
        "location": [
          113.390007,
          23.115856
        ],
        "sequence": 18
      },
      {
        "name": "东圃",
        "location": [
          113.401562,
          23.109392
        ],
        "sequence": 19
      },
      {
        "name": "三溪",
        "location": [
          113.415784,
          23.104098
        ],
        "sequence": 20
      },
      {
        "name": "鱼珠",
        "location": [
          113.432281,
          23.100343
        ],
        "sequence": 21
      },
      {
        "name": "大沙地",
        "location": [
          113.446074,
          23.103227
        ],
        "sequence": 22
      },
      {
        "name": "大沙东",
        "location": [
          113.458515,
          23.106216
        ],
        "sequence": 23
      },
      {
        "name": "文冲",
        "location": [
          113.469004,
          23.103796
        ],
        "sequence": 24
      },
      {
        "name": "双沙",
        "location": [
          113.484289,
          23.097877
        ],
        "sequence": 25
      },
      {
        "name": "庙头",
        "location": [
          113.502726,
          23.084731
        ],
        "sequence": 26
      },
      {
        "name": "夏园",
        "location": [
          113.518376,
          23.082901
        ],
        "sequence": 27
      },
      {
        "name": "保盈大道",
        "location": [
          113.526056,
          23.074279
        ],
        "sequence": 28
      },
      {
        "name": "夏港",
        "location": [
          113.525278,
          23.063541
        ],
        "sequence": 29
      },
      {
        "name": "黄埔新港",
        "location": [
          113.524819,
          23.052347
        ],
        "sequence": 30
      }
    ]
  }
}